{
  "timestamp": "2025-02-19 17:18:41",
  "total_entries": 16,
  "rankings": [
    {
      "position": 1,
      "class": {
        "en": "Wizard",
        "pt": "Mago",
        "short": "MA"
      },
      "name": "iPeiXe",
      "guild": "Out",
      "attack_power": 682051,
      "defense_power": 417835,
      "total_power": 1099886,
      "nation": {
        "en": "Capella",
        "pt": "Capella"
      }
    },
    {
      "position": 2,
      "class": {
        "en": "Wizard",
        "pt": "Mago",
        "short": "MA"
      },
      "name": "Gege",
      "guild": "ForsakenS",
      "attack_power": 618338,
      "defense_power": 372368,
      "total_power": 990706,
      "nation": {
        "en": "Procyon",
        "pt": "Procyon"
      }
    },
    {
      "position": 3,
      "class": {
        "en": "Wizard",
        "pt": "Mago",
        "short": "MA"
      },
      "name": "toMate",
      "guild": "ForsakenS",
      "attack_power": 605481,
      "defense_power": 360082,
      "total_power": 965563,
      "nation": {
        "en": "Procyon",
        "pt": "Procyon"
      }
    },
    {
      "position": 4,
      "class": {
        "en": "Wizard",
        "pt": "Mago",
        "short": "MA"
      },
      "name": "BritneyBitch",
      "guild": "ForsakenS",
      "attack_power": 563659,
      "defense_power": 354148,
      "total_power": 917807,
      "nation": {
        "en": "Procyon",
        "pt": "Procyon"
      }
    },
    {
      "position": 5,
      "class": {
        "en": "Wizard",
        "pt": "Mago",
        "short": "MA"
      },
      "name": "DarkAzazel",
      "guild": "ForsakenS",
      "attack_power": 574247,
      "defense_power": 339973,
      "total_power": 914220,
      "nation": {
        "en": "Procyon",
        "pt": "Procyon"
      }
    },
    {
      "position": 6,
      "class": {
        "en": "Wizard",
        "pt": "Mago",
        "short": "MA"
      },
      "name": "PadinhaXD",
      "guild": "ForsakenS",
      "attack_power": 571595,
      "defense_power": 333953,
      "total_power": 905548,
      "nation": {
        "en": "Procyon",
        "pt": "Procyon"
      }
    },
    {
      "position": 7,
      "class": {
        "en": "Wizard",
        "pt": "Mago",
        "short": "MA"
      },
      "name": "PANARO",
      "guild": "Out",
      "attack_power": 500017,
      "defense_power": 320278,
      "total_power": 820295,
      "nation": {
        "en": "Capella",
        "pt": "Capella"
      }
    },
    {
      "position": 8,
      "class": {
        "en": "Wizard",
        "pt": "Mago",
        "short": "MA"
      },
      "name": "Arkantos",
      "guild": "RealPlayers",
      "attack_power": 489942,
      "defense_power": 314099,
      "total_power": 804041,
      "nation": {
        "en": "Capella",
        "pt": "Capella"
      }
    },
    {
      "position": 9,
      "class": {
        "en": "Wizard",
        "pt": "Mago",
        "short": "MA"
      },
      "name": "LendaMA",
      "guild": "ForsakenS",
      "attack_power": 458874,
      "defense_power": 300726,
      "total_power": 759600,
      "nation": {
        "en": "Procyon",
        "pt": "Procyon"
      }
    },
    {
      "position": 10,
      "class": {
        "en": "Wizard",
        "pt": "Mago",
        "short": "MA"
      },
      "name": "Power",
      "guild": "Out",
      "attack_power": 429257,
      "defense_power": 300992,
      "total_power": 730249,
      "nation": {
        "en": "Capella",
        "pt": "Capella"
      }
    },
    {
      "position": 11,
      "class": {
        "en": "Wizard",
        "pt": "Mago",
        "short": "MA"
      },
      "name": "Page",
      "guild": "Sem guilda",
      "attack_power": 413583,
      "defense_power": 297409,
      "total_power": 710992,
      "nation": {
        "en": "Procyon",
        "pt": "Procyon"
      }
    },
    {
      "position": 12,
      "class": {
        "en": "Wizard",
        "pt": "Mago",
        "short": "MA"
      },
      "name": "Siriel",
      "guild": "ForsakenS",
      "attack_power": 434719,
      "defense_power": 263541,
      "total_power": 698260,
      "nation": {
        "en": "Procyon",
        "pt": "Procyon"
      }
    },
    {
      "position": 13,
      "class": {
        "en": "Wizard",
        "pt": "Mago",
        "short": "MA"
      },
      "name": "M4G4C0",
      "guild": "ForsakenS",
      "attack_power": 411557,
      "defense_power": 247137,
      "total_power": 658694,
      "nation": {
        "en": "Procyon",
        "pt": "Procyon"
      }
    },
    {
      "position": 14,
      "class": {
        "en": "Wizard",
        "pt": "Mago",
        "short": "MA"
      },
      "name": "iLisergia",
      "guild": "ForsakenS",
      "attack_power": 384907,
      "defense_power": 251381,
      "total_power": 636288,
      "nation": {
        "en": "Procyon",
        "pt": "Procyon"
      }
    },
    {
      "position": 15,
      "class": {
        "en": "Wizard",
        "pt": "Mago",
        "short": "MA"
      },
      "name": "Yuno",
      "guild": "ForsakenS",
      "attack_power": 376567,
      "defense_power": 257118,
      "total_power": 633685,
      "nation": {
        "en": "Procyon",
        "pt": "Procyon"
      }
    },
    {
      "position": 16,
      "class": {
        "en": "Wizard",
        "pt": "Mago",
        "short": "MA"
      },
      "name": "PollyxD",
      "guild": "SteinsKillerS",
      "attack_power": 393977,
      "defense_power": 229898,
      "total_power": 623875,
      "nation": {
        "en": "Capella",
        "pt": "Capella"
      }
    }
  ]
}