{
  "timestamp": "2025-02-19 21:17:54",
  "total_entries": 200,
  "rankings": [
    {
      "position": 1,
      "class": {
        "en": "Dark Mage",
        "pt": "Mago Negro",
        "short": "MN"
      },
      "name": "Abaddon",
      "guild": "Out",
      "attack_power": 833227,
      "defense_power": 541784,
      "total_power": 1375011,
      "nation": {
        "en": "Capella",
        "pt": "Capella"
      }
    },
    {
      "position": 2,
      "class": {
        "en": "Force Archer",
        "pt": "Arqueiro Arcano",
        "short": "AA"
      },
      "name": "DarkFeity",
      "guild": "Out",
      "attack_power": 832733,
      "defense_power": 461437,
      "total_power": 1294170,
      "nation": {
        "en": "Capella",
        "pt": "Capella"
      }
    },
    {
      "position": 3,
      "class": {
        "en": "Force Gunner",
        "pt": "Atirador",
        "short": "AT"
      },
      "name": "lLorD",
      "guild": "Out",
      "attack_power": 804748,
      "defense_power": 480319,
      "total_power": 1285067,
      "nation": {
        "en": "Capella",
        "pt": "Capella"
      }
    },
    {
      "position": 4,
      "class": {
        "en": "Dark Mage",
        "pt": "Mago Negro",
        "short": "MN"
      },
      "name": "xSrOKuMuRa",
      "guild": "ForsakenS",
      "attack_power": 814934,
      "defense_power": 452006,
      "total_power": 1266940,
      "nation": {
        "en": "Procyon",
        "pt": "Procyon"
      }
    },
    {
      "position": 5,
      "class": {
        "en": "Force Archer",
        "pt": "Arqueiro Arcano",
        "short": "AA"
      },
      "name": "Shimaru",
      "guild": "ForsakenS",
      "attack_power": 783672,
      "defense_power": 472549,
      "total_power": 1256221,
      "nation": {
        "en": "Procyon",
        "pt": "Procyon"
      }
    },
    {
      "position": 6,
      "class": {
        "en": "Blader",
        "pt": "Duelista",
        "short": "DU"
      },
      "name": "DreadHot",
      "guild": "ForsakenS",
      "attack_power": 766741,
      "defense_power": 451545,
      "total_power": 1218286,
      "nation": {
        "en": "Procyon",
        "pt": "Procyon"
      }
    },
    {
      "position": 7,
      "class": {
        "en": "Blader",
        "pt": "Duelista",
        "short": "DU"
      },
      "name": "Ro0b",
      "guild": "Out",
      "attack_power": 749746,
      "defense_power": 437899,
      "total_power": 1187645,
      "nation": {
        "en": "Capella",
        "pt": "Capella"
      }
    },
    {
      "position": 8,
      "class": {
        "en": "Dark Mage",
        "pt": "Mago Negro",
        "short": "MN"
      },
      "name": "RaphaDM",
      "guild": "Out",
      "attack_power": 723109,
      "defense_power": 435903,
      "total_power": 1159012,
      "nation": {
        "en": "Capella",
        "pt": "Capella"
      }
    },
    {
      "position": 9,
      "class": {
        "en": "Blader",
        "pt": "Duelista",
        "short": "DU"
      },
      "name": "Sortud0",
      "guild": "Out",
      "attack_power": 709197,
      "defense_power": 447122,
      "total_power": 1156319,
      "nation": {
        "en": "Capella",
        "pt": "Capella"
      }
    },
    {
      "position": 10,
      "class": {
        "en": "Warrior",
        "pt": "Guerreiro",
        "short": "GU"
      },
      "name": "HasgaKU",
      "guild": "ForsakenS",
      "attack_power": 698629,
      "defense_power": 449873,
      "total_power": 1148502,
      "nation": {
        "en": "Procyon",
        "pt": "Procyon"
      }
    },
    {
      "position": 11,
      "class": {
        "en": "Blader",
        "pt": "Duelista",
        "short": "DU"
      },
      "name": "K4PET4",
      "guild": "ForsakenS",
      "attack_power": 706848,
      "defense_power": 437361,
      "total_power": 1144209,
      "nation": {
        "en": "Procyon",
        "pt": "Procyon"
      }
    },
    {
      "position": 12,
      "class": {
        "en": "Force Archer",
        "pt": "Arqueiro Arcano",
        "short": "AA"
      },
      "name": "PiK4",
      "guild": "Out",
      "attack_power": 688285,
      "defense_power": 438870,
      "total_power": 1127155,
      "nation": {
        "en": "Capella",
        "pt": "Capella"
      }
    },
    {
      "position": 13,
      "class": {
        "en": "Force Gunner",
        "pt": "Atirador",
        "short": "AT"
      },
      "name": "JackJohnson",
      "guild": "ForsakenS",
      "attack_power": 705390,
      "defense_power": 417566,
      "total_power": 1122956,
      "nation": {
        "en": "Procyon",
        "pt": "Procyon"
      }
    },
    {
      "position": 14,
      "class": {
        "en": "Dark Mage",
        "pt": "Mago Negro",
        "short": "MN"
      },
      "name": "PorQuiNha",
      "guild": "ForsakenS",
      "attack_power": 708417,
      "defense_power": 399041,
      "total_power": 1107458,
      "nation": {
        "en": "Procyon",
        "pt": "Procyon"
      }
    },
    {
      "position": 15,
      "class": {
        "en": "Wizard",
        "pt": "Mago",
        "short": "MA"
      },
      "name": "iPeiXe",
      "guild": "Out",
      "attack_power": 671842,
      "defense_power": 410342,
      "total_power": 1082184,
      "nation": {
        "en": "Capella",
        "pt": "Capella"
      }
    },
    {
      "position": 16,
      "class": {
        "en": "Dark Mage",
        "pt": "Mago Negro",
        "short": "MN"
      },
      "name": "Xora",
      "guild": "Out",
      "attack_power": 697066,
      "defense_power": 385101,
      "total_power": 1082167,
      "nation": {
        "en": "Capella",
        "pt": "Capella"
      }
    },
    {
      "position": 17,
      "class": {
        "en": "Blader",
        "pt": "Duelista",
        "short": "DU"
      },
      "name": "M03D1NH4S",
      "guild": "ForsakenS",
      "attack_power": 698041,
      "defense_power": 380245,
      "total_power": 1078286,
      "nation": {
        "en": "Procyon",
        "pt": "Procyon"
      }
    },
    {
      "position": 18,
      "class": {
        "en": "Dark Mage",
        "pt": "Mago Negro",
        "short": "MN"
      },
      "name": "MarvadaXD",
      "guild": "Out",
      "attack_power": 682108,
      "defense_power": 388623,
      "total_power": 1070731,
      "nation": {
        "en": "Capella",
        "pt": "Capella"
      }
    },
    {
      "position": 19,
      "class": {
        "en": "Force Archer",
        "pt": "Arqueiro Arcano",
        "short": "AA"
      },
      "name": "Sonegadora",
      "guild": "Out",
      "attack_power": 574953,
      "defense_power": 492629,
      "total_power": 1067582,
      "nation": {
        "en": "Capella",
        "pt": "Capella"
      }
    },
    {
      "position": 20,
      "class": {
        "en": "Dark Mage",
        "pt": "Mago Negro",
        "short": "MN"
      },
      "name": "Trump",
      "guild": "Out",
      "attack_power": 691716,
      "defense_power": 371564,
      "total_power": 1063280,
      "nation": {
        "en": "Capella",
        "pt": "Capella"
      }
    },
    {
      "position": 21,
      "class": {
        "en": "Blader",
        "pt": "Duelista",
        "short": "DU"
      },
      "name": "AleRoX",
      "guild": "Out",
      "attack_power": 679160,
      "defense_power": 382130,
      "total_power": 1061290,
      "nation": {
        "en": "Capella",
        "pt": "Capella"
      }
    },
    {
      "position": 22,
      "class": {
        "en": "Dark Mage",
        "pt": "Mago Negro",
        "short": "MN"
      },
      "name": "Belzera",
      "guild": "Cursed",
      "attack_power": 670919,
      "defense_power": 386843,
      "total_power": 1057762,
      "nation": {
        "en": "Procyon",
        "pt": "Procyon"
      }
    },
    {
      "position": 23,
      "class": {
        "en": "Blader",
        "pt": "Duelista",
        "short": "DU"
      },
      "name": "rasec",
      "guild": "ForsakenS",
      "attack_power": 660719,
      "defense_power": 395066,
      "total_power": 1055785,
      "nation": {
        "en": "Procyon",
        "pt": "Procyon"
      }
    },
    {
      "position": 24,
      "class": {
        "en": "Force Blader",
        "pt": "Espadachim Arcano",
        "short": "EA"
      },
      "name": "1Monstrinho",
      "guild": "Out",
      "attack_power": 619568,
      "defense_power": 434703,
      "total_power": 1054271,
      "nation": {
        "en": "Capella",
        "pt": "Capella"
      }
    },
    {
      "position": 25,
      "class": {
        "en": "Force Archer",
        "pt": "Arqueiro Arcano",
        "short": "AA"
      },
      "name": "xKalista",
      "guild": "ForsakenS",
      "attack_power": 677267,
      "defense_power": 373676,
      "total_power": 1050943,
      "nation": {
        "en": "Procyon",
        "pt": "Procyon"
      }
    },
    {
      "position": 26,
      "class": {
        "en": "Blader",
        "pt": "Duelista",
        "short": "DU"
      },
      "name": "StressedOutt",
      "guild": "Out",
      "attack_power": 646877,
      "defense_power": 402799,
      "total_power": 1049676,
      "nation": {
        "en": "Capella",
        "pt": "Capella"
      }
    },
    {
      "position": 27,
      "class": {
        "en": "Dark Mage",
        "pt": "Mago Negro",
        "short": "MN"
      },
      "name": "Autoridade",
      "guild": "Out",
      "attack_power": 665632,
      "defense_power": 383905,
      "total_power": 1049537,
      "nation": {
        "en": "Capella",
        "pt": "Capella"
      }
    },
    {
      "position": 28,
      "class": {
        "en": "Force Shielder",
        "pt": "Guardião Arcano",
        "short": "GA"
      },
      "name": "Complicate",
      "guild": "ForsakenS",
      "attack_power": 602699,
      "defense_power": 424325,
      "total_power": 1027024,
      "nation": {
        "en": "Procyon",
        "pt": "Procyon"
      }
    },
    {
      "position": 29,
      "class": {
        "en": "Dark Mage",
        "pt": "Mago Negro",
        "short": "MN"
      },
      "name": "isMagic",
      "guild": "Out",
      "attack_power": 611921,
      "defense_power": 400482,
      "total_power": 1012403,
      "nation": {
        "en": "Capella",
        "pt": "Capella"
      }
    },
    {
      "position": 30,
      "class": {
        "en": "Force Blader",
        "pt": "Espadachim Arcano",
        "short": "EA"
      },
      "name": "Ortopedista",
      "guild": "ForsakenS",
      "attack_power": 589906,
      "defense_power": 411910,
      "total_power": 1001816,
      "nation": {
        "en": "Procyon",
        "pt": "Procyon"
      }
    },
    {
      "position": 31,
      "class": {
        "en": "Force Blader",
        "pt": "Espadachim Arcano",
        "short": "EA"
      },
      "name": "HelzaoXD38",
      "guild": "ForsakenS",
      "attack_power": 609711,
      "defense_power": 387464,
      "total_power": 997175,
      "nation": {
        "en": "Procyon",
        "pt": "Procyon"
      }
    },
    {
      "position": 32,
      "class": {
        "en": "Blader",
        "pt": "Duelista",
        "short": "DU"
      },
      "name": "ThanosXD",
      "guild": "ForsakenS",
      "attack_power": 614092,
      "defense_power": 381022,
      "total_power": 995114,
      "nation": {
        "en": "Procyon",
        "pt": "Procyon"
      }
    },
    {
      "position": 33,
      "class": {
        "en": "Force Gunner",
        "pt": "Atirador",
        "short": "AT"
      },
      "name": "Bambinho",
      "guild": "ForsakenS",
      "attack_power": 596280,
      "defense_power": 396135,
      "total_power": 992415,
      "nation": {
        "en": "Procyon",
        "pt": "Procyon"
      }
    },
    {
      "position": 34,
      "class": {
        "en": "Force Archer",
        "pt": "Arqueiro Arcano",
        "short": "AA"
      },
      "name": "Tanguete",
      "guild": "Out",
      "attack_power": 616384,
      "defense_power": 375568,
      "total_power": 991952,
      "nation": {
        "en": "Capella",
        "pt": "Capella"
      }
    },
    {
      "position": 35,
      "class": {
        "en": "Blader",
        "pt": "Duelista",
        "short": "DU"
      },
      "name": "BabySharkPDB",
      "guild": "Out",
      "attack_power": 609375,
      "defense_power": 380583,
      "total_power": 989958,
      "nation": {
        "en": "Capella",
        "pt": "Capella"
      }
    },
    {
      "position": 36,
      "class": {
        "en": "Dark Mage",
        "pt": "Mago Negro",
        "short": "MN"
      },
      "name": "TIPOmito",
      "guild": "Out",
      "attack_power": 621994,
      "defense_power": 367329,
      "total_power": 989323,
      "nation": {
        "en": "Capella",
        "pt": "Capella"
      }
    },
    {
      "position": 37,
      "class": {
        "en": "Wizard",
        "pt": "Mago",
        "short": "MA"
      },
      "name": "Gege",
      "guild": "ForsakenS",
      "attack_power": 618338,
      "defense_power": 370718,
      "total_power": 989056,
      "nation": {
        "en": "Procyon",
        "pt": "Procyon"
      }
    },
    {
      "position": 38,
      "class": {
        "en": "Dark Mage",
        "pt": "Mago Negro",
        "short": "MN"
      },
      "name": "R4v3n4",
      "guild": "ForsakenS",
      "attack_power": 602366,
      "defense_power": 378595,
      "total_power": 980961,
      "nation": {
        "en": "Procyon",
        "pt": "Procyon"
      }
    },
    {
      "position": 39,
      "class": {
        "en": "Dark Mage",
        "pt": "Mago Negro",
        "short": "MN"
      },
      "name": "Alfanabeto",
      "guild": "ForsakenS",
      "attack_power": 604034,
      "defense_power": 375022,
      "total_power": 979056,
      "nation": {
        "en": "Procyon",
        "pt": "Procyon"
      }
    },
    {
      "position": 40,
      "class": {
        "en": "Blader",
        "pt": "Duelista",
        "short": "DU"
      },
      "name": "vzeven2k",
      "guild": "Out",
      "attack_power": 588065,
      "defense_power": 387661,
      "total_power": 975726,
      "nation": {
        "en": "Capella",
        "pt": "Capella"
      }
    },
    {
      "position": 41,
      "class": {
        "en": "Wizard",
        "pt": "Mago",
        "short": "MA"
      },
      "name": "toMate",
      "guild": "ForsakenS",
      "attack_power": 601887,
      "defense_power": 358404,
      "total_power": 960291,
      "nation": {
        "en": "Procyon",
        "pt": "Procyon"
      }
    },
    {
      "position": 42,
      "class": {
        "en": "Force Archer",
        "pt": "Arqueiro Arcano",
        "short": "AA"
      },
      "name": "Inevit4vel",
      "guild": "ForsakenS",
      "attack_power": 597850,
      "defense_power": 355261,
      "total_power": 953111,
      "nation": {
        "en": "Procyon",
        "pt": "Procyon"
      }
    },
    {
      "position": 43,
      "class": {
        "en": "Dark Mage",
        "pt": "Mago Negro",
        "short": "MN"
      },
      "name": "Tedy",
      "guild": "ForsakenS",
      "attack_power": 570656,
      "defense_power": 380242,
      "total_power": 950898,
      "nation": {
        "en": "Procyon",
        "pt": "Procyon"
      }
    },
    {
      "position": 44,
      "class": {
        "en": "Blader",
        "pt": "Duelista",
        "short": "DU"
      },
      "name": "Titania",
      "guild": "ForsakenS",
      "attack_power": 562605,
      "defense_power": 385244,
      "total_power": 947849,
      "nation": {
        "en": "Procyon",
        "pt": "Procyon"
      }
    },
    {
      "position": 45,
      "class": {
        "en": "Force Archer",
        "pt": "Arqueiro Arcano",
        "short": "AA"
      },
      "name": "TaTuRaNa",
      "guild": "ForsakenS",
      "attack_power": 589692,
      "defense_power": 358060,
      "total_power": 947752,
      "nation": {
        "en": "Procyon",
        "pt": "Procyon"
      }
    },
    {
      "position": 46,
      "class": {
        "en": "Warrior",
        "pt": "Guerreiro",
        "short": "GU"
      },
      "name": "Belzebu",
      "guild": "ForsakenS",
      "attack_power": 558159,
      "defense_power": 384480,
      "total_power": 942639,
      "nation": {
        "en": "Procyon",
        "pt": "Procyon"
      }
    },
    {
      "position": 47,
      "class": {
        "en": "Blader",
        "pt": "Duelista",
        "short": "DU"
      },
      "name": "snkz",
      "guild": "Out",
      "attack_power": 561989,
      "defense_power": 379903,
      "total_power": 941892,
      "nation": {
        "en": "Capella",
        "pt": "Capella"
      }
    },
    {
      "position": 48,
      "class": {
        "en": "Force Shielder",
        "pt": "Guardião Arcano",
        "short": "GA"
      },
      "name": "AmostradinhoSK",
      "guild": "SteinsKillerS",
      "attack_power": 542021,
      "defense_power": 399433,
      "total_power": 941454,
      "nation": {
        "en": "Capella",
        "pt": "Capella"
      }
    },
    {
      "position": 49,
      "class": {
        "en": "Dark Mage",
        "pt": "Mago Negro",
        "short": "MN"
      },
      "name": "Terry",
      "guild": "ForsakenS",
      "attack_power": 550538,
      "defense_power": 388305,
      "total_power": 938843,
      "nation": {
        "en": "Procyon",
        "pt": "Procyon"
      }
    },
    {
      "position": 50,
      "class": {
        "en": "Blader",
        "pt": "Duelista",
        "short": "DU"
      },
      "name": "Enryu",
      "guild": "Out",
      "attack_power": 566321,
      "defense_power": 367992,
      "total_power": 934313,
      "nation": {
        "en": "Capella",
        "pt": "Capella"
      }
    },
    {
      "position": 51,
      "class": {
        "en": "Blader",
        "pt": "Duelista",
        "short": "DU"
      },
      "name": "DeusGarius",
      "guild": "Out",
      "attack_power": 552892,
      "defense_power": 375205,
      "total_power": 928097,
      "nation": {
        "en": "Capella",
        "pt": "Capella"
      }
    },
    {
      "position": 52,
      "class": {
        "en": "Wizard",
        "pt": "Mago",
        "short": "MA"
      },
      "name": "PadinhaXD",
      "guild": "ForsakenS",
      "attack_power": 577478,
      "defense_power": 345214,
      "total_power": 922692,
      "nation": {
        "en": "Procyon",
        "pt": "Procyon"
      }
    },
    {
      "position": 53,
      "class": {
        "en": "Dark Mage",
        "pt": "Mago Negro",
        "short": "MN"
      },
      "name": "DarkMage",
      "guild": "ForsakenS",
      "attack_power": 555332,
      "defense_power": 363457,
      "total_power": 918789,
      "nation": {
        "en": "Procyon",
        "pt": "Procyon"
      }
    },
    {
      "position": 54,
      "class": {
        "en": "Wizard",
        "pt": "Mago",
        "short": "MA"
      },
      "name": "BritneyBitch",
      "guild": "ForsakenS",
      "attack_power": 563659,
      "defense_power": 354148,
      "total_power": 917807,
      "nation": {
        "en": "Procyon",
        "pt": "Procyon"
      }
    },
    {
      "position": 55,
      "class": {
        "en": "Dark Mage",
        "pt": "Mago Negro",
        "short": "MN"
      },
      "name": "SaoCiprian0",
      "guild": "ForsakenS",
      "attack_power": 561687,
      "defense_power": 351504,
      "total_power": 913191,
      "nation": {
        "en": "Procyon",
        "pt": "Procyon"
      }
    },
    {
      "position": 56,
      "class": {
        "en": "Blader",
        "pt": "Duelista",
        "short": "DU"
      },
      "name": "Takeshi",
      "guild": "RealPlayers",
      "attack_power": 548853,
      "defense_power": 361607,
      "total_power": 910460,
      "nation": {
        "en": "Procyon",
        "pt": "Procyon"
      }
    },
    {
      "position": 57,
      "class": {
        "en": "Force Archer",
        "pt": "Arqueiro Arcano",
        "short": "AA"
      },
      "name": "Chefinho01",
      "guild": "SteinsKillerS",
      "attack_power": 576681,
      "defense_power": 333674,
      "total_power": 910355,
      "nation": {
        "en": "Capella",
        "pt": "Capella"
      }
    },
    {
      "position": 58,
      "class": {
        "en": "Dark Mage",
        "pt": "Mago Negro",
        "short": "MN"
      },
      "name": "Pardal",
      "guild": "Out",
      "attack_power": 567601,
      "defense_power": 341772,
      "total_power": 909373,
      "nation": {
        "en": "Capella",
        "pt": "Capella"
      }
    },
    {
      "position": 59,
      "class": {
        "en": "Dark Mage",
        "pt": "Mago Negro",
        "short": "MN"
      },
      "name": "xJinWoo",
      "guild": "Out",
      "attack_power": 560536,
      "defense_power": 345195,
      "total_power": 905731,
      "nation": {
        "en": "Capella",
        "pt": "Capella"
      }
    },
    {
      "position": 60,
      "class": {
        "en": "Wizard",
        "pt": "Mago",
        "short": "MA"
      },
      "name": "DarkAzazel",
      "guild": "ForsakenS",
      "attack_power": 565113,
      "defense_power": 340137,
      "total_power": 905250,
      "nation": {
        "en": "Procyon",
        "pt": "Procyon"
      }
    },
    {
      "position": 61,
      "class": {
        "en": "Dark Mage",
        "pt": "Mago Negro",
        "short": "MN"
      },
      "name": "Konig",
      "guild": "ForsakenS",
      "attack_power": 553637,
      "defense_power": 348782,
      "total_power": 902419,
      "nation": {
        "en": "Procyon",
        "pt": "Procyon"
      }
    },
    {
      "position": 62,
      "class": {
        "en": "Blader",
        "pt": "Duelista",
        "short": "DU"
      },
      "name": "lCavaUmaFalta",
      "guild": "SteinsKillerS",
      "attack_power": 573039,
      "defense_power": 325481,
      "total_power": 898520,
      "nation": {
        "en": "Capella",
        "pt": "Capella"
      }
    },
    {
      "position": 63,
      "class": {
        "en": "Blader",
        "pt": "Duelista",
        "short": "DU"
      },
      "name": "KevinMamar",
      "guild": "ForsakenS",
      "attack_power": 546472,
      "defense_power": 344824,
      "total_power": 891296,
      "nation": {
        "en": "Procyon",
        "pt": "Procyon"
      }
    },
    {
      "position": 64,
      "class": {
        "en": "Blader",
        "pt": "Duelista",
        "short": "DU"
      },
      "name": "BabaYaga",
      "guild": "Out",
      "attack_power": 537874,
      "defense_power": 348952,
      "total_power": 886826,
      "nation": {
        "en": "Capella",
        "pt": "Capella"
      }
    },
    {
      "position": 65,
      "class": {
        "en": "Blader",
        "pt": "Duelista",
        "short": "DU"
      },
      "name": "GorjinxGU",
      "guild": "Out",
      "attack_power": 531233,
      "defense_power": 351441,
      "total_power": 882674,
      "nation": {
        "en": "Capella",
        "pt": "Capella"
      }
    },
    {
      "position": 66,
      "class": {
        "en": "Blader",
        "pt": "Duelista",
        "short": "DU"
      },
      "name": "xMoonSTrinhAAx",
      "guild": "RealPlayers",
      "attack_power": 520190,
      "defense_power": 361583,
      "total_power": 881773,
      "nation": {
        "en": "Capella",
        "pt": "Capella"
      }
    },
    {
      "position": 67,
      "class": {
        "en": "Force Gunner",
        "pt": "Atirador",
        "short": "AT"
      },
      "name": "Furyy",
      "guild": "Out",
      "attack_power": 532450,
      "defense_power": 349058,
      "total_power": 881508,
      "nation": {
        "en": "Capella",
        "pt": "Capella"
      }
    },
    {
      "position": 68,
      "class": {
        "en": "Force Blader",
        "pt": "Espadachim Arcano",
        "short": "EA"
      },
      "name": "dragon666",
      "guild": "ForsakenS",
      "attack_power": 488159,
      "defense_power": 391722,
      "total_power": 879881,
      "nation": {
        "en": "Procyon",
        "pt": "Procyon"
      }
    },
    {
      "position": 69,
      "class": {
        "en": "Dark Mage",
        "pt": "Mago Negro",
        "short": "MN"
      },
      "name": "AFTERLIFE",
      "guild": "Out",
      "attack_power": 551368,
      "defense_power": 325765,
      "total_power": 877133,
      "nation": {
        "en": "Capella",
        "pt": "Capella"
      }
    },
    {
      "position": 70,
      "class": {
        "en": "Dark Mage",
        "pt": "Mago Negro",
        "short": "MN"
      },
      "name": "espinafre",
      "guild": "RealPlayers",
      "attack_power": 502172,
      "defense_power": 367852,
      "total_power": 870024,
      "nation": {
        "en": "Procyon",
        "pt": "Procyon"
      }
    },
    {
      "position": 71,
      "class": {
        "en": "Force Archer",
        "pt": "Arqueiro Arcano",
        "short": "AA"
      },
      "name": "PaiAmor",
      "guild": "ForsakenS",
      "attack_power": 511177,
      "defense_power": 355960,
      "total_power": 867137,
      "nation": {
        "en": "Procyon",
        "pt": "Procyon"
      }
    },
    {
      "position": 72,
      "class": {
        "en": "Blader",
        "pt": "Duelista",
        "short": "DU"
      },
      "name": "MARECHAS",
      "guild": "ForsakenS",
      "attack_power": 510820,
      "defense_power": 354284,
      "total_power": 865104,
      "nation": {
        "en": "Procyon",
        "pt": "Procyon"
      }
    },
    {
      "position": 73,
      "class": {
        "en": "Force Archer",
        "pt": "Arqueiro Arcano",
        "short": "AA"
      },
      "name": "iLulex",
      "guild": "Out",
      "attack_power": 517426,
      "defense_power": 346862,
      "total_power": 864288,
      "nation": {
        "en": "Capella",
        "pt": "Capella"
      }
    },
    {
      "position": 74,
      "class": {
        "en": "Dark Mage",
        "pt": "Mago Negro",
        "short": "MN"
      },
      "name": "NenelPDB",
      "guild": "Out",
      "attack_power": 511613,
      "defense_power": 348125,
      "total_power": 859738,
      "nation": {
        "en": "Capella",
        "pt": "Capella"
      }
    },
    {
      "position": 75,
      "class": {
        "en": "Force Shielder",
        "pt": "Guardião Arcano",
        "short": "GA"
      },
      "name": "Chopper",
      "guild": "ForsakenS",
      "attack_power": 467833,
      "defense_power": 389475,
      "total_power": 857308,
      "nation": {
        "en": "Procyon",
        "pt": "Procyon"
      }
    },
    {
      "position": 76,
      "class": {
        "en": "Blader",
        "pt": "Duelista",
        "short": "DU"
      },
      "name": "Sn0ok",
      "guild": "Out",
      "attack_power": 493846,
      "defense_power": 357334,
      "total_power": 851180,
      "nation": {
        "en": "Capella",
        "pt": "Capella"
      }
    },
    {
      "position": 77,
      "class": {
        "en": "Blader",
        "pt": "Duelista",
        "short": "DU"
      },
      "name": "CapitaoSteaK",
      "guild": "SteinsKillerS",
      "attack_power": 528607,
      "defense_power": 321777,
      "total_power": 850384,
      "nation": {
        "en": "Capella",
        "pt": "Capella"
      }
    },
    {
      "position": 78,
      "class": {
        "en": "Blader",
        "pt": "Duelista",
        "short": "DU"
      },
      "name": "Wanted",
      "guild": "ForsakenS",
      "attack_power": 504006,
      "defense_power": 345678,
      "total_power": 849684,
      "nation": {
        "en": "Procyon",
        "pt": "Procyon"
      }
    },
    {
      "position": 79,
      "class": {
        "en": "Blader",
        "pt": "Duelista",
        "short": "DU"
      },
      "name": "BladeMaster",
      "guild": "Out",
      "attack_power": 517898,
      "defense_power": 331324,
      "total_power": 849222,
      "nation": {
        "en": "Capella",
        "pt": "Capella"
      }
    },
    {
      "position": 80,
      "class": {
        "en": "Force Gunner",
        "pt": "Atirador",
        "short": "AT"
      },
      "name": "LadyGabi",
      "guild": "SteinsKillerS",
      "attack_power": 511770,
      "defense_power": 326040,
      "total_power": 837810,
      "nation": {
        "en": "Capella",
        "pt": "Capella"
      }
    },
    {
      "position": 81,
      "class": {
        "en": "Force Gunner",
        "pt": "Atirador",
        "short": "AT"
      },
      "name": "Flexinha",
      "guild": "RealPlayers",
      "attack_power": 500237,
      "defense_power": 335260,
      "total_power": 835497,
      "nation": {
        "en": "Procyon",
        "pt": "Procyon"
      }
    },
    {
      "position": 82,
      "class": {
        "en": "Force Shielder",
        "pt": "Guardião Arcano",
        "short": "GA"
      },
      "name": "PoderosoPDB",
      "guild": "Out",
      "attack_power": 489915,
      "defense_power": 344716,
      "total_power": 834631,
      "nation": {
        "en": "Capella",
        "pt": "Capella"
      }
    },
    {
      "position": 83,
      "class": {
        "en": "Force Archer",
        "pt": "Arqueiro Arcano",
        "short": "AA"
      },
      "name": "XxVENONxX",
      "guild": "RealPlayers",
      "attack_power": 489914,
      "defense_power": 341636,
      "total_power": 831550,
      "nation": {
        "en": "Procyon",
        "pt": "Procyon"
      }
    },
    {
      "position": 84,
      "class": {
        "en": "Warrior",
        "pt": "Guerreiro",
        "short": "GU"
      },
      "name": "Vivaz",
      "guild": "ForsakenS",
      "attack_power": 503631,
      "defense_power": 322252,
      "total_power": 825883,
      "nation": {
        "en": "Procyon",
        "pt": "Procyon"
      }
    },
    {
      "position": 85,
      "class": {
        "en": "Force Archer",
        "pt": "Arqueiro Arcano",
        "short": "AA"
      },
      "name": "BeBezinha",
      "guild": "Out",
      "attack_power": 486218,
      "defense_power": 338245,
      "total_power": 824463,
      "nation": {
        "en": "Capella",
        "pt": "Capella"
      }
    },
    {
      "position": 86,
      "class": {
        "en": "Blader",
        "pt": "Duelista",
        "short": "DU"
      },
      "name": "Powder",
      "guild": "ForsakenS",
      "attack_power": 486327,
      "defense_power": 337423,
      "total_power": 823750,
      "nation": {
        "en": "Procyon",
        "pt": "Procyon"
      }
    },
    {
      "position": 87,
      "class": {
        "en": "Gladiator",
        "pt": "Gladiador",
        "short": "GL"
      },
      "name": "FarmezinhaXD",
      "guild": "SteinsKillerS",
      "attack_power": 504197,
      "defense_power": 317112,
      "total_power": 821309,
      "nation": {
        "en": "Capella",
        "pt": "Capella"
      }
    },
    {
      "position": 88,
      "class": {
        "en": "Wizard",
        "pt": "Mago",
        "short": "MA"
      },
      "name": "Arkantos",
      "guild": "RealPlayers",
      "attack_power": 495843,
      "defense_power": 325189,
      "total_power": 821032,
      "nation": {
        "en": "Capella",
        "pt": "Capella"
      }
    },
    {
      "position": 89,
      "class": {
        "en": "Gladiator",
        "pt": "Gladiador",
        "short": "GL"
      },
      "name": "Zemiro",
      "guild": "SteinsKillerS",
      "attack_power": 498519,
      "defense_power": 322387,
      "total_power": 820906,
      "nation": {
        "en": "Capella",
        "pt": "Capella"
      }
    },
    {
      "position": 90,
      "class": {
        "en": "Force Blader",
        "pt": "Espadachim Arcano",
        "short": "EA"
      },
      "name": "Carlos",
      "guild": "Out",
      "attack_power": 455199,
      "defense_power": 365676,
      "total_power": 820875,
      "nation": {
        "en": "Capella",
        "pt": "Capella"
      }
    },
    {
      "position": 91,
      "class": {
        "en": "Wizard",
        "pt": "Mago",
        "short": "MA"
      },
      "name": "PANARO",
      "guild": "Out",
      "attack_power": 500017,
      "defense_power": 320278,
      "total_power": 820295,
      "nation": {
        "en": "Capella",
        "pt": "Capella"
      }
    },
    {
      "position": 92,
      "class": {
        "en": "Warrior",
        "pt": "Guerreiro",
        "short": "GU"
      },
      "name": "Paraiba",
      "guild": "ForsakenS",
      "attack_power": 504583,
      "defense_power": 313087,
      "total_power": 817670,
      "nation": {
        "en": "Procyon",
        "pt": "Procyon"
      }
    },
    {
      "position": 93,
      "class": {
        "en": "Dark Mage",
        "pt": "Mago Negro",
        "short": "MN"
      },
      "name": "SraGaladriel",
      "guild": "ForsakenS",
      "attack_power": 504473,
      "defense_power": 312551,
      "total_power": 817024,
      "nation": {
        "en": "Procyon",
        "pt": "Procyon"
      }
    },
    {
      "position": 94,
      "class": {
        "en": "Gladiator",
        "pt": "Gladiador",
        "short": "GL"
      },
      "name": "lShinobu",
      "guild": "ForsakenS",
      "attack_power": 460636,
      "defense_power": 356341,
      "total_power": 816977,
      "nation": {
        "en": "Procyon",
        "pt": "Procyon"
      }
    },
    {
      "position": 95,
      "class": {
        "en": "Force Archer",
        "pt": "Arqueiro Arcano",
        "short": "AA"
      },
      "name": "lRush",
      "guild": "Sem guilda",
      "attack_power": 488268,
      "defense_power": 327397,
      "total_power": 815665,
      "nation": {
        "en": "Capella",
        "pt": "Capella"
      }
    },
    {
      "position": 96,
      "class": {
        "en": "Blader",
        "pt": "Duelista",
        "short": "DU"
      },
      "name": "Roony",
      "guild": "1",
      "attack_power": 480339,
      "defense_power": 331840,
      "total_power": 812179,
      "nation": {
        "en": "Procyon",
        "pt": "Procyon"
      }
    },
    {
      "position": 97,
      "class": {
        "en": "Force Archer",
        "pt": "Arqueiro Arcano",
        "short": "AA"
      },
      "name": "J1nx",
      "guild": "SteinsKillerS",
      "attack_power": 470253,
      "defense_power": 341404,
      "total_power": 811657,
      "nation": {
        "en": "Capella",
        "pt": "Capella"
      }
    },
    {
      "position": 98,
      "class": {
        "en": "Blader",
        "pt": "Duelista",
        "short": "DU"
      },
      "name": "Alca",
      "guild": "Out",
      "attack_power": 486276,
      "defense_power": 320651,
      "total_power": 806927,
      "nation": {
        "en": "Capella",
        "pt": "Capella"
      }
    },
    {
      "position": 99,
      "class": {
        "en": "Force Shielder",
        "pt": "Guardião Arcano",
        "short": "GA"
      },
      "name": "Empire",
      "guild": "RealPlayers",
      "attack_power": 460863,
      "defense_power": 343199,
      "total_power": 804062,
      "nation": {
        "en": "Procyon",
        "pt": "Procyon"
      }
    },
    {
      "position": 100,
      "class": {
        "en": "Dark Mage",
        "pt": "Mago Negro",
        "short": "MN"
      },
      "name": "AmostradinhaSK",
      "guild": "SteinsKillerS",
      "attack_power": 498725,
      "defense_power": 304994,
      "total_power": 803719,
      "nation": {
        "en": "Capella",
        "pt": "Capella"
      }
    },
    {
      "position": 101,
      "class": {
        "en": "Dark Mage",
        "pt": "Mago Negro",
        "short": "MN"
      },
      "name": "XxAlyoshaxX",
      "guild": "Out",
      "attack_power": 491497,
      "defense_power": 311601,
      "total_power": 803098,
      "nation": {
        "en": "Capella",
        "pt": "Capella"
      }
    },
    {
      "position": 102,
      "class": {
        "en": "Blader",
        "pt": "Duelista",
        "short": "DU"
      },
      "name": "NEOTALINDO",
      "guild": "Sem guilda",
      "attack_power": 489537,
      "defense_power": 313261,
      "total_power": 802798,
      "nation": {
        "en": "Procyon",
        "pt": "Procyon"
      }
    },
    {
      "position": 103,
      "class": {
        "en": "Force Archer",
        "pt": "Arqueiro Arcano",
        "short": "AA"
      },
      "name": "TreKer",
      "guild": "Out",
      "attack_power": 461227,
      "defense_power": 333869,
      "total_power": 795096,
      "nation": {
        "en": "Capella",
        "pt": "Capella"
      }
    },
    {
      "position": 104,
      "class": {
        "en": "Force Archer",
        "pt": "Arqueiro Arcano",
        "short": "AA"
      },
      "name": "ThriisTham",
      "guild": "SteinsKillerS",
      "attack_power": 477364,
      "defense_power": 317033,
      "total_power": 794397,
      "nation": {
        "en": "Capella",
        "pt": "Capella"
      }
    },
    {
      "position": 105,
      "class": {
        "en": "Force Gunner",
        "pt": "Atirador",
        "short": "AT"
      },
      "name": "Sylvie",
      "guild": "SteinsKillerS",
      "attack_power": 480998,
      "defense_power": 304063,
      "total_power": 785061,
      "nation": {
        "en": "Capella",
        "pt": "Capella"
      }
    },
    {
      "position": 106,
      "class": {
        "en": "Blader",
        "pt": "Duelista",
        "short": "DU"
      },
      "name": "SOLDADO",
      "guild": "ForsakenS",
      "attack_power": 462691,
      "defense_power": 321883,
      "total_power": 784574,
      "nation": {
        "en": "Procyon",
        "pt": "Procyon"
      }
    },
    {
      "position": 107,
      "class": {
        "en": "Dark Mage",
        "pt": "Mago Negro",
        "short": "MN"
      },
      "name": "Padinha",
      "guild": "ForsakenS",
      "attack_power": 460981,
      "defense_power": 311791,
      "total_power": 772772,
      "nation": {
        "en": "Procyon",
        "pt": "Procyon"
      }
    },
    {
      "position": 108,
      "class": {
        "en": "Warrior",
        "pt": "Guerreiro",
        "short": "GU"
      },
      "name": "MAriaBonita",
      "guild": "Out",
      "attack_power": 447252,
      "defense_power": 325135,
      "total_power": 772387,
      "nation": {
        "en": "Capella",
        "pt": "Capella"
      }
    },
    {
      "position": 109,
      "class": {
        "en": "Dark Mage",
        "pt": "Mago Negro",
        "short": "MN"
      },
      "name": "Lemrak",
      "guild": "RealPlayers",
      "attack_power": 478801,
      "defense_power": 290841,
      "total_power": 769642,
      "nation": {
        "en": "Capella",
        "pt": "Capella"
      }
    },
    {
      "position": 110,
      "class": {
        "en": "Dark Mage",
        "pt": "Mago Negro",
        "short": "MN"
      },
      "name": "xThrax",
      "guild": "SteinsKillerS",
      "attack_power": 486788,
      "defense_power": 278517,
      "total_power": 765305,
      "nation": {
        "en": "Procyon",
        "pt": "Procyon"
      }
    },
    {
      "position": 111,
      "class": {
        "en": "Force Archer",
        "pt": "Arqueiro Arcano",
        "short": "AA"
      },
      "name": "Kyndar",
      "guild": "Out",
      "attack_power": 465609,
      "defense_power": 297710,
      "total_power": 763319,
      "nation": {
        "en": "Capella",
        "pt": "Capella"
      }
    },
    {
      "position": 112,
      "class": {
        "en": "Dark Mage",
        "pt": "Mago Negro",
        "short": "MN"
      },
      "name": "YpiocaPrataXD",
      "guild": "SteinsKillerS",
      "attack_power": 476464,
      "defense_power": 286803,
      "total_power": 763267,
      "nation": {
        "en": "Capella",
        "pt": "Capella"
      }
    },
    {
      "position": 113,
      "class": {
        "en": "Blader",
        "pt": "Duelista",
        "short": "DU"
      },
      "name": "PoliDU",
      "guild": "RealPlayers",
      "attack_power": 450313,
      "defense_power": 311054,
      "total_power": 761367,
      "nation": {
        "en": "Capella",
        "pt": "Capella"
      }
    },
    {
      "position": 114,
      "class": {
        "en": "Blader",
        "pt": "Duelista",
        "short": "DU"
      },
      "name": "BIGOLINHAA",
      "guild": "Out",
      "attack_power": 458336,
      "defense_power": 302922,
      "total_power": 761258,
      "nation": {
        "en": "Procyon",
        "pt": "Procyon"
      }
    },
    {
      "position": 115,
      "class": {
        "en": "Wizard",
        "pt": "Mago",
        "short": "MA"
      },
      "name": "LendaMA",
      "guild": "ForsakenS",
      "attack_power": 458874,
      "defense_power": 300726,
      "total_power": 759600,
      "nation": {
        "en": "Procyon",
        "pt": "Procyon"
      }
    },
    {
      "position": 116,
      "class": {
        "en": "Force Blader",
        "pt": "Espadachim Arcano",
        "short": "EA"
      },
      "name": "yMucillon",
      "guild": "Sem guilda",
      "attack_power": 447636,
      "defense_power": 311204,
      "total_power": 758840,
      "nation": {
        "en": "Capella",
        "pt": "Capella"
      }
    },
    {
      "position": 117,
      "class": {
        "en": "Blader",
        "pt": "Duelista",
        "short": "DU"
      },
      "name": "OMNITRIX",
      "guild": "ForsakenS",
      "attack_power": 445392,
      "defense_power": 310413,
      "total_power": 755805,
      "nation": {
        "en": "Procyon",
        "pt": "Procyon"
      }
    },
    {
      "position": 118,
      "class": {
        "en": "Gladiator",
        "pt": "Gladiador",
        "short": "GL"
      },
      "name": "DeMonSs",
      "guild": "RealPlayers",
      "attack_power": 431182,
      "defense_power": 323891,
      "total_power": 755073,
      "nation": {
        "en": "Capella",
        "pt": "Capella"
      }
    },
    {
      "position": 119,
      "class": {
        "en": "Force Shielder",
        "pt": "Guardião Arcano",
        "short": "GA"
      },
      "name": "DaniMozao",
      "guild": "Out",
      "attack_power": 446676,
      "defense_power": 307411,
      "total_power": 754087,
      "nation": {
        "en": "Capella",
        "pt": "Capella"
      }
    },
    {
      "position": 120,
      "class": {
        "en": "Blader",
        "pt": "Duelista",
        "short": "DU"
      },
      "name": "Rick",
      "guild": "ForsakenS",
      "attack_power": 460063,
      "defense_power": 290946,
      "total_power": 751009,
      "nation": {
        "en": "Procyon",
        "pt": "Procyon"
      }
    },
    {
      "position": 121,
      "class": {
        "en": "Blader",
        "pt": "Duelista",
        "short": "DU"
      },
      "name": "Axel",
      "guild": "ForsakenS",
      "attack_power": 449360,
      "defense_power": 299786,
      "total_power": 749146,
      "nation": {
        "en": "Procyon",
        "pt": "Procyon"
      }
    },
    {
      "position": 122,
      "class": {
        "en": "Blader",
        "pt": "Duelista",
        "short": "DU"
      },
      "name": "Observad0R",
      "guild": "SteinsKillerS",
      "attack_power": 453935,
      "defense_power": 290182,
      "total_power": 744117,
      "nation": {
        "en": "Capella",
        "pt": "Capella"
      }
    },
    {
      "position": 123,
      "class": {
        "en": "Warrior",
        "pt": "Guerreiro",
        "short": "GU"
      },
      "name": "AmyKun",
      "guild": "RealPlayers",
      "attack_power": 445204,
      "defense_power": 298696,
      "total_power": 743900,
      "nation": {
        "en": "Capella",
        "pt": "Capella"
      }
    },
    {
      "position": 124,
      "class": {
        "en": "Force Archer",
        "pt": "Arqueiro Arcano",
        "short": "AA"
      },
      "name": "Only",
      "guild": "RealPlayers",
      "attack_power": 444655,
      "defense_power": 295648,
      "total_power": 740303,
      "nation": {
        "en": "Procyon",
        "pt": "Procyon"
      }
    },
    {
      "position": 125,
      "class": {
        "en": "Dark Mage",
        "pt": "Mago Negro",
        "short": "MN"
      },
      "name": "EvilBilleJoe",
      "guild": "Out",
      "attack_power": 431673,
      "defense_power": 307141,
      "total_power": 738814,
      "nation": {
        "en": "Capella",
        "pt": "Capella"
      }
    },
    {
      "position": 126,
      "class": {
        "en": "Blader",
        "pt": "Duelista",
        "short": "DU"
      },
      "name": "Full",
      "guild": "ForsakenS",
      "attack_power": 426016,
      "defense_power": 305438,
      "total_power": 731454,
      "nation": {
        "en": "Procyon",
        "pt": "Procyon"
      }
    },
    {
      "position": 127,
      "class": {
        "en": "Wizard",
        "pt": "Mago",
        "short": "MA"
      },
      "name": "Power",
      "guild": "Out",
      "attack_power": 429257,
      "defense_power": 300992,
      "total_power": 730249,
      "nation": {
        "en": "Capella",
        "pt": "Capella"
      }
    },
    {
      "position": 128,
      "class": {
        "en": "Force Archer",
        "pt": "Arqueiro Arcano",
        "short": "AA"
      },
      "name": "CloseUP",
      "guild": "Out",
      "attack_power": 438131,
      "defense_power": 291985,
      "total_power": 730116,
      "nation": {
        "en": "Capella",
        "pt": "Capella"
      }
    },
    {
      "position": 129,
      "class": {
        "en": "Blader",
        "pt": "Duelista",
        "short": "DU"
      },
      "name": "SrKruegeer",
      "guild": "SteinsKillerS",
      "attack_power": 427184,
      "defense_power": 302371,
      "total_power": 729555,
      "nation": {
        "en": "Capella",
        "pt": "Capella"
      }
    },
    {
      "position": 130,
      "class": {
        "en": "Warrior",
        "pt": "Guerreiro",
        "short": "GU"
      },
      "name": "formigaoDOcaps",
      "guild": "ForsakenS",
      "attack_power": 420876,
      "defense_power": 302281,
      "total_power": 723157,
      "nation": {
        "en": "Procyon",
        "pt": "Procyon"
      }
    },
    {
      "position": 131,
      "class": {
        "en": "Force Archer",
        "pt": "Arqueiro Arcano",
        "short": "AA"
      },
      "name": "thiloki",
      "guild": "C4",
      "attack_power": 413389,
      "defense_power": 309075,
      "total_power": 722464,
      "nation": {
        "en": "Procyon",
        "pt": "Procyon"
      }
    },
    {
      "position": 132,
      "class": {
        "en": "Warrior",
        "pt": "Guerreiro",
        "short": "GU"
      },
      "name": "BaltasaR",
      "guild": "ForsakenS",
      "attack_power": 420388,
      "defense_power": 302025,
      "total_power": 722413,
      "nation": {
        "en": "Procyon",
        "pt": "Procyon"
      }
    },
    {
      "position": 133,
      "class": {
        "en": "Blader",
        "pt": "Duelista",
        "short": "DU"
      },
      "name": "Highlander",
      "guild": "ForsakenS",
      "attack_power": 437208,
      "defense_power": 285049,
      "total_power": 722257,
      "nation": {
        "en": "Procyon",
        "pt": "Procyon"
      }
    },
    {
      "position": 134,
      "class": {
        "en": "Blader",
        "pt": "Duelista",
        "short": "DU"
      },
      "name": "MasterFX",
      "guild": "Out",
      "attack_power": 430216,
      "defense_power": 284951,
      "total_power": 715167,
      "nation": {
        "en": "Capella",
        "pt": "Capella"
      }
    },
    {
      "position": 135,
      "class": {
        "en": "Blader",
        "pt": "Duelista",
        "short": "DU"
      },
      "name": "WalkeeR",
      "guild": "RealPlayers",
      "attack_power": 423828,
      "defense_power": 290449,
      "total_power": 714277,
      "nation": {
        "en": "Capella",
        "pt": "Capella"
      }
    },
    {
      "position": 136,
      "class": {
        "en": "Wizard",
        "pt": "Mago",
        "short": "MA"
      },
      "name": "Page",
      "guild": "Sem guilda",
      "attack_power": 413583,
      "defense_power": 297409,
      "total_power": 710992,
      "nation": {
        "en": "Procyon",
        "pt": "Procyon"
      }
    },
    {
      "position": 137,
      "class": {
        "en": "Warrior",
        "pt": "Guerreiro",
        "short": "GU"
      },
      "name": "MarquinllGU",
      "guild": "C4",
      "attack_power": 410128,
      "defense_power": 299513,
      "total_power": 709641,
      "nation": {
        "en": "Procyon",
        "pt": "Procyon"
      }
    },
    {
      "position": 138,
      "class": {
        "en": "Force Blader",
        "pt": "Espadachim Arcano",
        "short": "EA"
      },
      "name": "Leozinx777",
      "guild": "ForsakenS",
      "attack_power": 407089,
      "defense_power": 299325,
      "total_power": 706414,
      "nation": {
        "en": "Procyon",
        "pt": "Procyon"
      }
    },
    {
      "position": 139,
      "class": {
        "en": "Blader",
        "pt": "Duelista",
        "short": "DU"
      },
      "name": "SraFruitJuice",
      "guild": "Out",
      "attack_power": 429393,
      "defense_power": 276719,
      "total_power": 706112,
      "nation": {
        "en": "Capella",
        "pt": "Capella"
      }
    },
    {
      "position": 140,
      "class": {
        "en": "Dark Mage",
        "pt": "Mago Negro",
        "short": "MN"
      },
      "name": "VingaDora",
      "guild": "Sem guilda",
      "attack_power": 425983,
      "defense_power": 276557,
      "total_power": 702540,
      "nation": {
        "en": "Procyon",
        "pt": "Procyon"
      }
    },
    {
      "position": 141,
      "class": {
        "en": "Dark Mage",
        "pt": "Mago Negro",
        "short": "MN"
      },
      "name": "Kyllbyll",
      "guild": "Out",
      "attack_power": 425255,
      "defense_power": 271444,
      "total_power": 696699,
      "nation": {
        "en": "Procyon",
        "pt": "Procyon"
      }
    },
    {
      "position": 142,
      "class": {
        "en": "Blader",
        "pt": "Duelista",
        "short": "DU"
      },
      "name": "Donner",
      "guild": "RealPlayers",
      "attack_power": 423706,
      "defense_power": 272919,
      "total_power": 696625,
      "nation": {
        "en": "Capella",
        "pt": "Capella"
      }
    },
    {
      "position": 143,
      "class": {
        "en": "Warrior",
        "pt": "Guerreiro",
        "short": "GU"
      },
      "name": "MasterChief117",
      "guild": "Sem guilda",
      "attack_power": 423054,
      "defense_power": 273110,
      "total_power": 696164,
      "nation": {
        "en": "Procyon",
        "pt": "Procyon"
      }
    },
    {
      "position": 144,
      "class": {
        "en": "Dark Mage",
        "pt": "Mago Negro",
        "short": "MN"
      },
      "name": "Hyoga",
      "guild": "ForsakenS",
      "attack_power": 420445,
      "defense_power": 275049,
      "total_power": 695494,
      "nation": {
        "en": "Procyon",
        "pt": "Procyon"
      }
    },
    {
      "position": 145,
      "class": {
        "en": "Warrior",
        "pt": "Guerreiro",
        "short": "GU"
      },
      "name": "TiTioSlash",
      "guild": "Cursed",
      "attack_power": 391267,
      "defense_power": 303862,
      "total_power": 695129,
      "nation": {
        "en": "Procyon",
        "pt": "Procyon"
      }
    },
    {
      "position": 146,
      "class": {
        "en": "Warrior",
        "pt": "Guerreiro",
        "short": "GU"
      },
      "name": "BiruXD",
      "guild": "Cursed",
      "attack_power": 401482,
      "defense_power": 291923,
      "total_power": 693405,
      "nation": {
        "en": "Capella",
        "pt": "Capella"
      }
    },
    {
      "position": 147,
      "class": {
        "en": "Force Archer",
        "pt": "Arqueiro Arcano",
        "short": "AA"
      },
      "name": "LeaziXCIII",
      "guild": "SteinsKillerS",
      "attack_power": 386926,
      "defense_power": 304375,
      "total_power": 691301,
      "nation": {
        "en": "Capella",
        "pt": "Capella"
      }
    },
    {
      "position": 148,
      "class": {
        "en": "Force Gunner",
        "pt": "Atirador",
        "short": "AT"
      },
      "name": "Amor",
      "guild": "RealPlayers",
      "attack_power": 416885,
      "defense_power": 267459,
      "total_power": 684344,
      "nation": {
        "en": "Procyon",
        "pt": "Procyon"
      }
    },
    {
      "position": 149,
      "class": {
        "en": "Blader",
        "pt": "Duelista",
        "short": "DU"
      },
      "name": "iS3R3IA",
      "guild": "RealPlayers",
      "attack_power": 399591,
      "defense_power": 283929,
      "total_power": 683520,
      "nation": {
        "en": "Procyon",
        "pt": "Procyon"
      }
    },
    {
      "position": 150,
      "class": {
        "en": "Force Archer",
        "pt": "Arqueiro Arcano",
        "short": "AA"
      },
      "name": "Bloody",
      "guild": "RealPlayers",
      "attack_power": 394770,
      "defense_power": 286901,
      "total_power": 681671,
      "nation": {
        "en": "Procyon",
        "pt": "Procyon"
      }
    },
    {
      "position": 151,
      "class": {
        "en": "Blader",
        "pt": "Duelista",
        "short": "DU"
      },
      "name": "YunaZ0r",
      "guild": "Sem guilda",
      "attack_power": 402260,
      "defense_power": 278492,
      "total_power": 680752,
      "nation": {
        "en": "Procyon",
        "pt": "Procyon"
      }
    },
    {
      "position": 152,
      "class": {
        "en": "Warrior",
        "pt": "Guerreiro",
        "short": "GU"
      },
      "name": "Colossal",
      "guild": "Out",
      "attack_power": 407242,
      "defense_power": 268020,
      "total_power": 675262,
      "nation": {
        "en": "Capella",
        "pt": "Capella"
      }
    },
    {
      "position": 153,
      "class": {
        "en": "Blader",
        "pt": "Duelista",
        "short": "DU"
      },
      "name": "Vovo",
      "guild": "Sem guilda",
      "attack_power": 376398,
      "defense_power": 297573,
      "total_power": 673971,
      "nation": {
        "en": "Capella",
        "pt": "Capella"
      }
    },
    {
      "position": 154,
      "class": {
        "en": "Dark Mage",
        "pt": "Mago Negro",
        "short": "MN"
      },
      "name": "Afromaxx",
      "guild": "Toxic",
      "attack_power": 408502,
      "defense_power": 264389,
      "total_power": 672891,
      "nation": {
        "en": "Capella",
        "pt": "Capella"
      }
    },
    {
      "position": 155,
      "class": {
        "en": "Force Gunner",
        "pt": "Atirador",
        "short": "AT"
      },
      "name": "SementeMalignus",
      "guild": "Cursed",
      "attack_power": 413693,
      "defense_power": 258725,
      "total_power": 672418,
      "nation": {
        "en": "Procyon",
        "pt": "Procyon"
      }
    },
    {
      "position": 156,
      "class": {
        "en": "Gladiator",
        "pt": "Gladiador",
        "short": "GL"
      },
      "name": "BAYGON",
      "guild": "Out",
      "attack_power": 376393,
      "defense_power": 294945,
      "total_power": 671338,
      "nation": {
        "en": "Capella",
        "pt": "Capella"
      }
    },
    {
      "position": 157,
      "class": {
        "en": "Dark Mage",
        "pt": "Mago Negro",
        "short": "MN"
      },
      "name": "SexyMachine",
      "guild": "ForsakenS",
      "attack_power": 394458,
      "defense_power": 273132,
      "total_power": 667590,
      "nation": {
        "en": "Procyon",
        "pt": "Procyon"
      }
    },
    {
      "position": 158,
      "class": {
        "en": "Blader",
        "pt": "Duelista",
        "short": "DU"
      },
      "name": "Claw",
      "guild": "Cursed",
      "attack_power": 388052,
      "defense_power": 278813,
      "total_power": 666865,
      "nation": {
        "en": "Capella",
        "pt": "Capella"
      }
    },
    {
      "position": 159,
      "class": {
        "en": "Blader",
        "pt": "Duelista",
        "short": "DU"
      },
      "name": "Cumpadi",
      "guild": "ForsakenS",
      "attack_power": 395390,
      "defense_power": 270184,
      "total_power": 665574,
      "nation": {
        "en": "Procyon",
        "pt": "Procyon"
      }
    },
    {
      "position": 160,
      "class": {
        "en": "Force Blader",
        "pt": "Espadachim Arcano",
        "short": "EA"
      },
      "name": "VenOnXD",
      "guild": "ForsakenS",
      "attack_power": 392097,
      "defense_power": 271837,
      "total_power": 663934,
      "nation": {
        "en": "Procyon",
        "pt": "Procyon"
      }
    },
    {
      "position": 161,
      "class": {
        "en": "Blader",
        "pt": "Duelista",
        "short": "DU"
      },
      "name": "CassiusXD",
      "guild": "Cursed",
      "attack_power": 399436,
      "defense_power": 263557,
      "total_power": 662993,
      "nation": {
        "en": "Capella",
        "pt": "Capella"
      }
    },
    {
      "position": 162,
      "class": {
        "en": "Blader",
        "pt": "Duelista",
        "short": "DU"
      },
      "name": "MrFloid",
      "guild": "ForsakenS",
      "attack_power": 404486,
      "defense_power": 256649,
      "total_power": 661135,
      "nation": {
        "en": "Procyon",
        "pt": "Procyon"
      }
    },
    {
      "position": 163,
      "class": {
        "en": "Blader",
        "pt": "Duelista",
        "short": "DU"
      },
      "name": "ImPush",
      "guild": "Cursed",
      "attack_power": 395783,
      "defense_power": 264935,
      "total_power": 660718,
      "nation": {
        "en": "Capella",
        "pt": "Capella"
      }
    },
    {
      "position": 164,
      "class": {
        "en": "Blader",
        "pt": "Duelista",
        "short": "DU"
      },
      "name": "NinaWilliiams",
      "guild": "ForsakenS",
      "attack_power": 392714,
      "defense_power": 267697,
      "total_power": 660411,
      "nation": {
        "en": "Procyon",
        "pt": "Procyon"
      }
    },
    {
      "position": 165,
      "class": {
        "en": "Wizard",
        "pt": "Mago",
        "short": "MA"
      },
      "name": "Siriel",
      "guild": "ForsakenS",
      "attack_power": 420143,
      "defense_power": 240081,
      "total_power": 660224,
      "nation": {
        "en": "Procyon",
        "pt": "Procyon"
      }
    },
    {
      "position": 166,
      "class": {
        "en": "Dark Mage",
        "pt": "Mago Negro",
        "short": "MN"
      },
      "name": "grennpark",
      "guild": "RealPlayers",
      "attack_power": 392821,
      "defense_power": 266583,
      "total_power": 659404,
      "nation": {
        "en": "Capella",
        "pt": "Capella"
      }
    },
    {
      "position": 167,
      "class": {
        "en": "Dark Mage",
        "pt": "Mago Negro",
        "short": "MN"
      },
      "name": "xDias",
      "guild": "ForsakenS",
      "attack_power": 389125,
      "defense_power": 269654,
      "total_power": 658779,
      "nation": {
        "en": "Procyon",
        "pt": "Procyon"
      }
    },
    {
      "position": 168,
      "class": {
        "en": "Wizard",
        "pt": "Mago",
        "short": "MA"
      },
      "name": "M4G4C0",
      "guild": "ForsakenS",
      "attack_power": 411557,
      "defense_power": 247137,
      "total_power": 658694,
      "nation": {
        "en": "Procyon",
        "pt": "Procyon"
      }
    },
    {
      "position": 169,
      "class": {
        "en": "Force Archer",
        "pt": "Arqueiro Arcano",
        "short": "AA"
      },
      "name": "DanFoster",
      "guild": "ForsakenS",
      "attack_power": 388256,
      "defense_power": 266773,
      "total_power": 655029,
      "nation": {
        "en": "Procyon",
        "pt": "Procyon"
      }
    },
    {
      "position": 170,
      "class": {
        "en": "Blader",
        "pt": "Duelista",
        "short": "DU"
      },
      "name": "Star",
      "guild": "Cursed",
      "attack_power": 390677,
      "defense_power": 261395,
      "total_power": 652072,
      "nation": {
        "en": "Procyon",
        "pt": "Procyon"
      }
    },
    {
      "position": 171,
      "class": {
        "en": "Force Shielder",
        "pt": "Guardião Arcano",
        "short": "GA"
      },
      "name": "LionSin",
      "guild": "Out",
      "attack_power": 381003,
      "defense_power": 269408,
      "total_power": 650411,
      "nation": {
        "en": "Capella",
        "pt": "Capella"
      }
    },
    {
      "position": 172,
      "class": {
        "en": "Blader",
        "pt": "Duelista",
        "short": "DU"
      },
      "name": "Levi",
      "guild": "Sem guilda",
      "attack_power": 385687,
      "defense_power": 264151,
      "total_power": 649838,
      "nation": {
        "en": "Capella",
        "pt": "Capella"
      }
    },
    {
      "position": 173,
      "class": {
        "en": "Dark Mage",
        "pt": "Mago Negro",
        "short": "MN"
      },
      "name": "SidMatarazzo",
      "guild": "Out",
      "attack_power": 381239,
      "defense_power": 266958,
      "total_power": 648197,
      "nation": {
        "en": "Capella",
        "pt": "Capella"
      }
    },
    {
      "position": 174,
      "class": {
        "en": "Wizard",
        "pt": "Mago",
        "short": "MA"
      },
      "name": "PollyxD",
      "guild": "SteinsKillerS",
      "attack_power": 417544,
      "defense_power": 229898,
      "total_power": 647442,
      "nation": {
        "en": "Capella",
        "pt": "Capella"
      }
    },
    {
      "position": 175,
      "class": {
        "en": "Dark Mage",
        "pt": "Mago Negro",
        "short": "MN"
      },
      "name": "KillerBGameR",
      "guild": "Out",
      "attack_power": 380080,
      "defense_power": 266919,
      "total_power": 646999,
      "nation": {
        "en": "Capella",
        "pt": "Capella"
      }
    },
    {
      "position": 176,
      "class": {
        "en": "Dark Mage",
        "pt": "Mago Negro",
        "short": "MN"
      },
      "name": "SELEUMAMOU",
      "guild": "Sem guilda",
      "attack_power": 383047,
      "defense_power": 261345,
      "total_power": 644392,
      "nation": {
        "en": "Capella",
        "pt": "Capella"
      }
    },
    {
      "position": 177,
      "class": {
        "en": "Warrior",
        "pt": "Guerreiro",
        "short": "GU"
      },
      "name": "Bob999",
      "guild": "RusheSolo",
      "attack_power": 370601,
      "defense_power": 270137,
      "total_power": 640738,
      "nation": {
        "en": "Procyon",
        "pt": "Procyon"
      }
    },
    {
      "position": 178,
      "class": {
        "en": "Warrior",
        "pt": "Guerreiro",
        "short": "GU"
      },
      "name": "JonesBurgo",
      "guild": "Out",
      "attack_power": 410589,
      "defense_power": 229567,
      "total_power": 640156,
      "nation": {
        "en": "Procyon",
        "pt": "Procyon"
      }
    },
    {
      "position": 179,
      "class": {
        "en": "Dark Mage",
        "pt": "Mago Negro",
        "short": "MN"
      },
      "name": "oOCaPiiRoToO",
      "guild": "SteinsKillerS",
      "attack_power": 366128,
      "defense_power": 273355,
      "total_power": 639483,
      "nation": {
        "en": "Capella",
        "pt": "Capella"
      }
    },
    {
      "position": 180,
      "class": {
        "en": "Blader",
        "pt": "Duelista",
        "short": "DU"
      },
      "name": "HelzaoXdDU",
      "guild": "Sem guilda",
      "attack_power": 395185,
      "defense_power": 244109,
      "total_power": 639294,
      "nation": {
        "en": "Capella",
        "pt": "Capella"
      }
    },
    {
      "position": 181,
      "class": {
        "en": "Gladiator",
        "pt": "Gladiador",
        "short": "GL"
      },
      "name": "Graviton",
      "guild": "ForsakenS",
      "attack_power": 357539,
      "defense_power": 279342,
      "total_power": 636881,
      "nation": {
        "en": "Procyon",
        "pt": "Procyon"
      }
    },
    {
      "position": 182,
      "class": {
        "en": "Wizard",
        "pt": "Mago",
        "short": "MA"
      },
      "name": "iLisergia",
      "guild": "ForsakenS",
      "attack_power": 384907,
      "defense_power": 251381,
      "total_power": 636288,
      "nation": {
        "en": "Procyon",
        "pt": "Procyon"
      }
    },
    {
      "position": 183,
      "class": {
        "en": "Force Archer",
        "pt": "Arqueiro Arcano",
        "short": "AA"
      },
      "name": "Demonho",
      "guild": "Imaculados",
      "attack_power": 371054,
      "defense_power": 264370,
      "total_power": 635424,
      "nation": {
        "en": "Procyon",
        "pt": "Procyon"
      }
    },
    {
      "position": 184,
      "class": {
        "en": "Force Shielder",
        "pt": "Guardião Arcano",
        "short": "GA"
      },
      "name": "zlDuratestoN",
      "guild": "Sem guilda",
      "attack_power": 356708,
      "defense_power": 277594,
      "total_power": 634302,
      "nation": {
        "en": "Procyon",
        "pt": "Procyon"
      }
    },
    {
      "position": 185,
      "class": {
        "en": "Wizard",
        "pt": "Mago",
        "short": "MA"
      },
      "name": "Yuno",
      "guild": "ForsakenS",
      "attack_power": 376567,
      "defense_power": 257118,
      "total_power": 633685,
      "nation": {
        "en": "Procyon",
        "pt": "Procyon"
      }
    },
    {
      "position": 186,
      "class": {
        "en": "Force Blader",
        "pt": "Espadachim Arcano",
        "short": "EA"
      },
      "name": "XxNamIxX",
      "guild": "RealPlayers",
      "attack_power": 376822,
      "defense_power": 254340,
      "total_power": 631162,
      "nation": {
        "en": "Capella",
        "pt": "Capella"
      }
    },
    {
      "position": 187,
      "class": {
        "en": "Blader",
        "pt": "Duelista",
        "short": "DU"
      },
      "name": "BLACKMARIA",
      "guild": "RealPlayers",
      "attack_power": 377531,
      "defense_power": 250860,
      "total_power": 628391,
      "nation": {
        "en": "Procyon",
        "pt": "Procyon"
      }
    },
    {
      "position": 188,
      "class": {
        "en": "Force Blader",
        "pt": "Espadachim Arcano",
        "short": "EA"
      },
      "name": "EspadaXin",
      "guild": "C4",
      "attack_power": 358773,
      "defense_power": 268045,
      "total_power": 626818,
      "nation": {
        "en": "Procyon",
        "pt": "Procyon"
      }
    },
    {
      "position": 189,
      "class": {
        "en": "Dark Mage",
        "pt": "Mago Negro",
        "short": "MN"
      },
      "name": "TomattaoGAUCHO",
      "guild": "Cursed",
      "attack_power": 378338,
      "defense_power": 248134,
      "total_power": 626472,
      "nation": {
        "en": "Procyon",
        "pt": "Procyon"
      }
    },
    {
      "position": 190,
      "class": {
        "en": "Blader",
        "pt": "Duelista",
        "short": "DU"
      },
      "name": "XIIxyraxIIX",
      "guild": "SteinsKillerS",
      "attack_power": 360875,
      "defense_power": 264191,
      "total_power": 625066,
      "nation": {
        "en": "Capella",
        "pt": "Capella"
      }
    },
    {
      "position": 191,
      "class": {
        "en": "Blader",
        "pt": "Duelista",
        "short": "DU"
      },
      "name": "Loser",
      "guild": "SteinsKillerS",
      "attack_power": 373834,
      "defense_power": 251194,
      "total_power": 625028,
      "nation": {
        "en": "Capella",
        "pt": "Capella"
      }
    },
    {
      "position": 192,
      "class": {
        "en": "Force Archer",
        "pt": "Arqueiro Arcano",
        "short": "AA"
      },
      "name": "KrooZ",
      "guild": "ForsakenS",
      "attack_power": 371924,
      "defense_power": 251928,
      "total_power": 623852,
      "nation": {
        "en": "Procyon",
        "pt": "Procyon"
      }
    },
    {
      "position": 193,
      "class": {
        "en": "Blader",
        "pt": "Duelista",
        "short": "DU"
      },
      "name": "KhansaDU",
      "guild": "ForsakenS",
      "attack_power": 380266,
      "defense_power": 242580,
      "total_power": 622846,
      "nation": {
        "en": "Procyon",
        "pt": "Procyon"
      }
    },
    {
      "position": 194,
      "class": {
        "en": "Blader",
        "pt": "Duelista",
        "short": "DU"
      },
      "name": "lLeonaa",
      "guild": "RealPlayers",
      "attack_power": 368556,
      "defense_power": 252871,
      "total_power": 621427,
      "nation": {
        "en": "Procyon",
        "pt": "Procyon"
      }
    },
    {
      "position": 195,
      "class": {
        "en": "Warrior",
        "pt": "Guerreiro",
        "short": "GU"
      },
      "name": "SemSonoXD",
      "guild": "SteinsKillerS",
      "attack_power": 367480,
      "defense_power": 253769,
      "total_power": 621249,
      "nation": {
        "en": "Capella",
        "pt": "Capella"
      }
    },
    {
      "position": 196,
      "class": {
        "en": "Force Archer",
        "pt": "Arqueiro Arcano",
        "short": "AA"
      },
      "name": "Goodz",
      "guild": "Sem guilda",
      "attack_power": 367601,
      "defense_power": 252034,
      "total_power": 619635,
      "nation": {
        "en": "Procyon",
        "pt": "Procyon"
      }
    },
    {
      "position": 197,
      "class": {
        "en": "Gladiator",
        "pt": "Gladiador",
        "short": "GL"
      },
      "name": "GUR1L4",
      "guild": "ForsakenS",
      "attack_power": 350414,
      "defense_power": 267297,
      "total_power": 617711,
      "nation": {
        "en": "Procyon",
        "pt": "Procyon"
      }
    },
    {
      "position": 198,
      "class": {
        "en": "Force Archer",
        "pt": "Arqueiro Arcano",
        "short": "AA"
      },
      "name": "TomTom",
      "guild": "ForsakenS",
      "attack_power": 370450,
      "defense_power": 247180,
      "total_power": 617630,
      "nation": {
        "en": "Procyon",
        "pt": "Procyon"
      }
    },
    {
      "position": 199,
      "class": {
        "en": "Force Gunner",
        "pt": "Atirador",
        "short": "AT"
      },
      "name": "KatenKyokotsu",
      "guild": "Cursed",
      "attack_power": 369281,
      "defense_power": 248234,
      "total_power": 617515,
      "nation": {
        "en": "Capella",
        "pt": "Capella"
      }
    },
    {
      "position": 200,
      "class": {
        "en": "Warrior",
        "pt": "Guerreiro",
        "short": "GU"
      },
      "name": "xEuaKaKau",
      "guild": "SteinsKillerS",
      "attack_power": 351753,
      "defense_power": 265577,
      "total_power": 617330,
      "nation": {
        "en": "Procyon",
        "pt": "Procyon"
      }
    }
  ]
}